pcc.py
pccgui.py
utils.py
command_center-0.0.6.dist-info/METADATA
command_center-0.0.6.dist-info/RECORD
command_center-0.0.6.dist-info/WHEEL
command_center-0.0.6.dist-info/entry_points.txt
command_center-0.0.6.dist-info/top_level.txt
