Metadata-Version: 2.1
Name: command-center
Version: 0.0.6
Summary: Quick method for running frequently used terminal commands.
Home-page: https://github.com/miniscruff/python-command-center
Author: Ronnie Smith
Author-email: halfpint1170@gmail.com
License: UNKNOWN
Project-URL: Bug Reports, https://github.com/miniscruff/python-command-center/issues
Project-URL: Source, https://github.com/miniscruff/python-command-center
Keywords: development
Platform: UNKNOWN
Classifier: Development Status :: 3 - Alpha
Classifier: Intended Audience :: Developers
Classifier: Topic :: Software Development :: Build Tools
Classifier: License :: OSI Approved :: MIT License
Classifier: Programming Language :: Python :: 3.6
Requires-Dist: click
